tabular_ml/__init__.py
tabular_ml/base.py
tabular_ml/factory.py
tabular_ml/functions.py
tabular_ml/utilities.py
tabular_ml/ml_models/__init__.py
tabular_ml/ml_models/catboost_model.py
tabular_ml/ml_models/lgbm_model.py
tabular_ml/ml_models/linear_models.py
tabular_ml/ml_models/xgboost_model.py
tabular_ml-0.0.2.dist-info/METADATA
tabular_ml-0.0.2.dist-info/WHEEL
tabular_ml-0.0.2.dist-info/top_level.txt
tabular_ml-0.0.2.dist-info/RECORD
