Metadata-Version: 2.1
Name: tabular-ml
Version: 0.0.2
Summary: This library wraps popular tabular regression/classification model enabling rapid evaluation and optimization.
Author-email: Xavier Nogueira <xavier.rojas.nogueira@gmail.com>
Keywords: machine-learning,pipeline,factory,tabular,regression,classification
Classifier: Development Status :: 5 - Production/Stable
Classifier: Intended Audience :: Science/Research
Classifier: Operating System :: OS Independent
Classifier: License :: OSI Approved :: BSD License
Classifier: Programming Language :: Python
Classifier: Programming Language :: Python :: 3
Classifier: Programming Language :: Python :: 3.11
Classifier: Topic :: Scientific/Engineering
Requires-Python: >=3.11
Requires-Dist: pandas
Requires-Dist: numpy
Requires-Dist: scipy
Requires-Dist: scikit-learn
Requires-Dist: optuna
Requires-Dist: xgboost
Requires-Dist: catboost
Requires-Dist: lightgbm
